holowizard/__init__.py
holowizard/logo.png
holowizard/core/LICENSE
holowizard/core/__init__.py
holowizard/core/api/__init__.py
holowizard/core/api/functions/__init__.py
holowizard/core/api/functions/default_load_data_callback.py
holowizard/core/api/functions/find_focus/__init__.py
holowizard/core/api/functions/find_focus/find_focus.py
holowizard/core/api/functions/find_focus/find_focus_flatfieldcorrection.py
holowizard/core/api/functions/find_focus/find_focus_flatfieldcorrection_io.py
holowizard/core/api/functions/find_focus/find_focus_z01_a0.py
holowizard/core/api/functions/find_focus/find_focus_z01_a0_flatfieldcorrection.py
holowizard/core/api/functions/flatfield_correction/__init__.py
holowizard/core/api/functions/flatfield_correction/calc_flatfield_components_io.py
holowizard/core/api/functions/flatfield_correction/calc_flatfield_components_o.py
holowizard/core/api/functions/flatfield_correction/flatfield_correction_i.py
holowizard/core/api/functions/flatfield_correction/get_synthetic_flatfield.py
holowizard/core/api/functions/probe_retrieval/__init__.py
holowizard/core/api/functions/probe_retrieval/reconstruction.py
holowizard/core/api/functions/single_projection/__init__.py
holowizard/core/api/functions/single_projection/reconstruction.py
holowizard/core/api/functions/single_projection/reconstruction_flatfieldcorrection.py
holowizard/core/api/functions/single_projection/reconstruction_flatfieldcorrection_i.py
holowizard/core/api/functions/single_projection/reconstruction_flatfieldcorrection_io.py
holowizard/core/api/functions/single_projection/reconstruction_io.py
holowizard/core/api/parameters/__init__.py
holowizard/core/api/parameters/beam_setup.py
holowizard/core/api/parameters/dask_options.py
holowizard/core/api/parameters/data_dimensions.py
holowizard/core/api/parameters/flatfield_components_params.py
holowizard/core/api/parameters/flatfield_correction_params.py
holowizard/core/api/parameters/measurement.py
holowizard/core/api/parameters/options.py
holowizard-1.1.14.dist-info/licenses/LICENSE
holowizard-1.1.14.dist-info/licenses/holowizard/core/LICENSE
holowizard-1.1.14.dist-info/licenses/holowizard/forge/LICENSE
holowizard-1.1.14.dist-info/licenses/holowizard/pipe/LICENSE
holowizard-1.1.14.dist-info/METADATA
holowizard-1.1.14.dist-info/WHEEL
holowizard-1.1.14.dist-info/entry_points.txt
holowizard-1.1.14.dist-info/top_level.txt
holowizard-1.1.14.dist-info/RECORD
