Metadata-Version: 2.4
Name: holowizard
Version: 1.1.14
Author-email: Johannes Dora <johannes.dora@desy.de>, Johannes Hagemann <johannes.hagemann@desy.de>, André Lopes <andre.lopes@hereon.de>, Johannes Hagemann <johannes.hagemann@desy.de>, Silja Flenner <silja.flenner@hereon.de>, Johannes Grün <johannes.gruen@desy.de>, Sebastian Eberle <sebastian.eberle@desy.de>, Cem Cinar <cem.cinar@tuhh.de>
Maintainer-email: Johannes Dora <johannes.dora@desy.de>, André Lopes <andre.lopes@hereon.de>, Johannes Grün <johannes.gruen@desy.de>, Sebastian Eberle <sebastian.eberle@desy.de>, Johannes Hagemann <johannes.hagemann@desy.de>
License-Expression: MIT
Project-URL: Repository, https://github.com/DESY-FS-PETRA/holowizard
Project-URL: Paper_ASRM, https://doi.org/10.1364/OE.514641
Project-URL: Paper_Autofocus, https://doi.org/10.1364/OE.544573
Project-URL: Zenodo, https://doi.org/10.5281/zenodo.8349364
Keywords: near-field holography,phase retrieval,tomography
Classifier: Programming Language :: Python
Requires-Python: <3.12,>=3.11
License-File: LICENSE
License-File: holowizard/forge/LICENSE
License-File: holowizard/core/LICENSE
License-File: holowizard/pipe/LICENSE
Requires-Dist: tqdm
Requires-Dist: numpy==1.26.4
Requires-Dist: torch
Requires-Dist: torchvision
Requires-Dist: matplotlib
Requires-Dist: pandas
Requires-Dist: h5py
Requires-Dist: hdf5plugin
Requires-Dist: selenium
Requires-Dist: bs4
Requires-Dist: requests
Requires-Dist: xraylib
Requires-Dist: cupy-cuda12x
Requires-Dist: pyzmq
Requires-Dist: pyqt5-tools
Requires-Dist: scikit-learn
Requires-Dist: scikit-image
Requires-Dist: GitPython
Requires-Dist: dask
Requires-Dist: dask_jobqueue
Requires-Dist: pytest
Requires-Dist: bokeh
Requires-Dist: scipy
Requires-Dist: astra-toolbox
Requires-Dist: pyqtgraph
Requires-Dist: uvicorn
Requires-Dist: hydra-core
Requires-Dist: fastapi[standard]
Requires-Dist: markdown
Requires-Dist: plotly
Dynamic: license-file
